input_plus/__init__.py
input_plus/input_date.py
input_plus/input_func.py
input_plus/input_password.py
input_plus/input_plus.py
input_plus/input_regex.py
input_plus/input_select.py
input_plus-0.2.1.dist-info/LICENSE.txt
input_plus-0.2.1.dist-info/METADATA
input_plus-0.2.1.dist-info/WHEEL
input_plus-0.2.1.dist-info/top_level.txt
input_plus-0.2.1.dist-info/RECORD
