Metadata-Version: 2.2
Name: input-plus
Version: 0.2.1
Summary: A Python package.
License-File: LICENSE.txt
Requires-Dist: Levenshtein~=0.25.1
Requires-Dist: python-Levenshtein~=0.25.1
Requires-Dist: rapidfuzz~=3.9.2
